ipfabric_netbox/__init__.py
ipfabric_netbox/api/__init__.py
ipfabric_netbox/api/serializers.py
ipfabric_netbox/api/urls.py
ipfabric_netbox/api/views.py
ipfabric_netbox/choices.py
ipfabric_netbox/data/transform_map.json
ipfabric_netbox/exceptions.py
ipfabric_netbox/filtersets.py
ipfabric_netbox/forms.py
ipfabric_netbox/graphql/__init__.py
ipfabric_netbox/graphql/enums.py
ipfabric_netbox/graphql/filters.py
ipfabric_netbox/graphql/schema.py
ipfabric_netbox/graphql/types.py
ipfabric_netbox/jobs.py
ipfabric_netbox/migrations/0001_initial.py
ipfabric_netbox/migrations/0001_initial_squashed_0013_switch_to_branching_plugin.py
ipfabric_netbox/migrations/0002_ipfabricsnapshot_status.py
ipfabric_netbox/migrations/0003_ipfabricsource_type_and_more.py
ipfabric_netbox/migrations/0004_ipfabricsync_auto_merge.py
ipfabric_netbox/migrations/0005_alter_ipfabricrelationshipfield_source_model_and_more.py
ipfabric_netbox/migrations/0006_alter_ipfabrictransformmap_target_model.py
ipfabric_netbox/migrations/0007_prepare_custom_fields.py
ipfabric_netbox/migrations/0008_prepare_transform_maps.py
ipfabric_netbox/migrations/0009_transformmap_changes_for_netbox_v4_2.py
ipfabric_netbox/migrations/0010_remove_uuid_from_get_or_create.py
ipfabric_netbox/migrations/0011_update_part_number_DCIM_inventory_item_template.py
ipfabric_netbox/migrations/0012_remove_status_field.py
ipfabric_netbox/migrations/0013_switch_to_branching_plugin.py
ipfabric_netbox/migrations/0014_ipfabrictransformmapgroup_ipfabrictransformmap_group.py
ipfabric_netbox/migrations/0015_ipfabricingestionissue.py
ipfabric_netbox/migrations/0016_tags_and_changelog_for_snapshots.py
ipfabric_netbox/migrations/0017_ipfabricsync_update_custom_fields.py
ipfabric_netbox/migrations/0018_remove_type_field.py
ipfabric_netbox/migrations/0019_alter_ipfabrictransformmap_options_and_more.py
ipfabric_netbox/migrations/0020_clean_scheduled_jobs.py
ipfabric_netbox/migrations/__init__.py
ipfabric_netbox/models.py
ipfabric_netbox/navigation.py
ipfabric_netbox-4.3.1.dist-info/METADATA
ipfabric_netbox-4.3.1.dist-info/WHEEL
ipfabric_netbox-4.3.1.dist-info/RECORD
