Metadata-Version: 2.4
Name: ipfabric_netbox
Version: 4.3.1
Summary: NetBox plugin to sync IP Fabric data into NetBox
License: MIT
Keywords: netbox,ipfabric,plugin,sync
Author: Solution Architecture
Author-email: solution.architecture@ipfabric.io
Requires-Python: >=3.10,<4.0
Classifier: License :: OSI Approved :: MIT License
Classifier: Operating System :: OS Independent
Classifier: Programming Language :: Python :: 3
Classifier: Programming Language :: Python :: 3.10
Classifier: Programming Language :: Python :: 3.11
Classifier: Programming Language :: Python :: 3.12
Classifier: Programming Language :: Python :: 3.13
Classifier: Programming Language :: Python :: 3.14
Provides-Extra: ipfabric-6-10
Provides-Extra: ipfabric-7-0
Provides-Extra: ipfabric-7-2
Provides-Extra: ipfabric-7-3
Requires-Dist: ipfabric (>=6.10.0,<6.11.0) ; extra == "ipfabric_6_10" and extra != "ipfabric_7_0" and extra != "ipfabric_7_2" and extra != "ipfabric_7_3"
Requires-Dist: ipfabric (>=6.6.4) ; extra != "ipfabric_6_10" and extra != "ipfabric_7_0" and extra != "ipfabric_7_2" and extra != "ipfabric_7_3"
Requires-Dist: ipfabric (>=7.0.0,<7.1.0) ; extra != "ipfabric_6_10" and extra == "ipfabric_7_0" and extra != "ipfabric_7_2" and extra != "ipfabric_7_3"
Requires-Dist: ipfabric (>=7.2.0,<7.3.0) ; extra != "ipfabric_6_10" and extra != "ipfabric_7_0" and extra == "ipfabric_7_2" and extra != "ipfabric_7_3"
Requires-Dist: ipfabric (>=7.3.0,<7.4.0) ; extra != "ipfabric_6_10" and extra != "ipfabric_7_0" and extra != "ipfabric_7_2" and extra == "ipfabric_7_3"
Requires-Dist: netboxlabs-netbox-branching (==0.7.0)
Requires-Dist: netutils
Project-URL: Bug Tracker, https://gitlab.com/ip-fabric/integrations/ipfabric-netbox-sync/-/issues
Project-URL: Homepage, https://gitlab.com/ip-fabric/integrations/ipfabric-netbox-sync
Project-URL: Repository, https://gitlab.com/ip-fabric/integrations/ipfabric-netbox-sync
